mindmap_mcp_server/__init__.py
mindmap_mcp_server/server.py
mindmap_mcp_server-0.1.1.dist-info/METADATA
mindmap_mcp_server-0.1.1.dist-info/WHEEL
mindmap_mcp_server-0.1.1.dist-info/entry_points.txt
mindmap_mcp_server-0.1.1.dist-info/licenses/LICENSE
mindmap_mcp_server-0.1.1.dist-info/RECORD
