Metadata-Version: 2.4
Name: mindmap-mcp-server
Version: 0.1.1
Summary: MCP server for converting Markdown to mindmaps
Project-URL: Homepage, https://github.com/YuChenSSR/mindmap-mcp-server
Project-URL: Bug Tracker, https://github.com/YuChenSSR/mindmap-mcp-server/issues
Author: YuChenSSR
License: MIT License
License-File: LICENSE
Keywords: ai,claude,markdown,mcp,mindmap
Classifier: Development Status :: 4 - Beta
Classifier: Intended Audience :: Developers
Classifier: License :: OSI Approved :: MIT License
Classifier: Programming Language :: Python :: 3
Classifier: Programming Language :: Python :: 3.10
Classifier: Programming Language :: Python :: 3.11
Classifier: Topic :: Software Development :: Libraries
Requires-Python: >=3.10
Requires-Dist: mcp>=1.2.0
